README.md
__init__.py
conftest.py
libtbx_refresh.py
setup.py
Applications/__init__.py
Applications/xia2_helpers.py
Applications/xia2_main.py
Applications/xia2ccp4i.py
Applications/xia2merger.py
Applications/xia2setup.py
Applications/xia2setup_helpers.py
Background/Background.py
Background/__init__.py
Decorators/CCP4Decorator.py
Decorators/DecoratorFactory.py
Decorators/__init__.py
Driver/ClusterDriverFactory.py
Driver/DefaultClusterDriver.py
Driver/DefaultDriver.py
Driver/DriverFactory.py
Driver/DriverHelper.py
Driver/InteractiveDriver.py
Driver/PythonDriver.py
Driver/QSubDriver.py
Driver/ScriptDriver.py
Driver/SimpleDriver.py
Driver/SunGridEngineClusterDriver.py
Driver/__init__.py
Driver/test_ClusterDriverFactory.py
Driver/test_DriverFactory.py
Driver/test_timing.py
Driver/timing.py
DriverExceptions/NotAvailableError.py
DriverExceptions/__init__.py
Experts/Filenames.py
Experts/FindImages.py
Experts/LatticeExpert.py
Experts/MatrixExpert.py
Experts/MissetExpert.py
Experts/ReferenceFrame.py
Experts/ResolutionExperts.py
Experts/SymmetryExpert.py
Experts/WedgeExpert.py
Experts/__init__.py
GUI/__init__.py
GUI/dataset.py
Handlers/CIF.py
Handlers/Citations.py
Handlers/CommandLine.py
Handlers/Environment.py
Handlers/Files.py
Handlers/Flags.py
Handlers/Phil.py
Handlers/PipelineSelection.py
Handlers/Streams.py
Handlers/Syminfo.py
Handlers/XInfo.py
Handlers/__init__.py
Interfaces/__init__.py
Interfaces/ISPyB/ISPyBXmlHandler.py
Interfaces/ISPyB/__init__.py
Modules/AnalyseMyIntensities.py
Modules/CCP4InterRadiationDamageDetector.py
Modules/CctbxFrenchWilson.py
Modules/DeltaCcHalf.py
Modules/DoseAccumulate.py
Modules/FindFreeFlag.py
Modules/GainEstimater.py
Modules/LabelitBeamCentre.py
Modules/MtzUtils.py
Modules/Mtzdump.py
Modules/MultiCrystalAnalysis.py
Modules/UnitCellErrors.py
Modules/UnpackByteOffset.py
Modules/XDS_ASCII.py
Modules/__init__.py
Modules/Analysis/__init__.py
Modules/Indexer/DialsIndexer.py
Modules/Indexer/IndexerFactory.py
xia2.egg-info/PKG-INFO
xia2.egg-info/SOURCES.txt
xia2.egg-info/dependency_links.txt
xia2.egg-info/not-zip-safe
xia2.egg-info/requires.txt
xia2.egg-info/top_level.txt